dehug/__init__.py
dehug/exceptions.py
dehug/repository.py
dehug/utils.py
dehug-0.2.2.dist-info/METADATA
dehug-0.2.2.dist-info/WHEEL
dehug-0.2.2.dist-info/entry_points.txt
dehug-0.2.2.dist-info/top_level.txt
dehug-0.2.2.dist-info/RECORD
