Metadata-Version: 2.4
Name: dehug
Version: 0.2.2
Summary: Decentralized Hugging Face - AI models and datasets from IPFS/Filecoin
Home-page: https://github.com/olagold-hackxx/dehug
Author: DeHug Team
Author-email: contact@dehug.io
Project-URL: Bug Tracker, https://github.com/olagold-hackxx/dehug/issues
Project-URL: Documentation, https://docs.dehug.io
Project-URL: Source Code, https://github.com/olagold-hackxx/dehug
Classifier: Development Status :: 3 - Alpha
Classifier: Intended Audience :: Developers
Classifier: Intended Audience :: Science/Research
Classifier: License :: OSI Approved :: Apache Software License
Classifier: Operating System :: OS Independent
Classifier: Programming Language :: Python :: 3
Classifier: Programming Language :: Python :: 3.8
Classifier: Programming Language :: Python :: 3.9
Classifier: Programming Language :: Python :: 3.10
Classifier: Programming Language :: Python :: 3.11
Classifier: Programming Language :: Python :: 3.12
Classifier: Topic :: Scientific/Engineering :: Artificial Intelligence
Classifier: Topic :: Software Development :: Libraries :: Python Modules
Requires-Python: >=3.8
Requires-Dist: requests>=2.31.0
Requires-Dist: pandas>=2.0.0
Requires-Dist: pyarrow>=14.0.1
Dynamic: author
Dynamic: author-email
Dynamic: classifier
Dynamic: description
Dynamic: description-content-type
Dynamic: home-page
Dynamic: project-url
Dynamic: requires-dist
Dynamic: requires-python
Dynamic: summary
